{"cameraMode":{"drawMode":0,"name":"Shaded","section":"Shading Mode"},"sceneLighting":false,"audioPlay":false,"sceneViewState":{"showFog":true,"showMaterialUpdate":false,"showSkybox":false,"showFlares":true,"showImageEffects":true,"showParticleSystems":true},"in2DMode":false,"pivot":{"x":0.04000002145767212,"y":0.37695351243019106,"z":0.31638866662979128},"rotation":{"x":-0.3112993538379669,"y":-0.06891046464443207,"z":0.022660912945866586,"w":-0.9476328492164612},"size":1.2532058954238892,"orthographic":false}